.gitlab-ci.yml
.travis.yml
CHANGES.rst
CONTRIBUTORS.rst
DEVELOP.rst
LICENSE.GPL
LICENSE.rst
MANIFEST.in
README.rst
constraints.txt
constraints_plone43.txt
constraints_plone50.txt
constraints_plone51.txt
constraints_plone52.txt
requirements.txt
setup.cfg
setup.py
tox.ini
docs/conf.py
docs/index.rst
src/cs/__init__.py
src/cs.ploneformdemo.egg-info/PKG-INFO
src/cs.ploneformdemo.egg-info/SOURCES.txt
src/cs.ploneformdemo.egg-info/dependency_links.txt
src/cs.ploneformdemo.egg-info/entry_points.txt
src/cs.ploneformdemo.egg-info/namespace_packages.txt
src/cs.ploneformdemo.egg-info/not-zip-safe
src/cs.ploneformdemo.egg-info/requires.txt
src/cs.ploneformdemo.egg-info/top_level.txt
src/cs/ploneformdemo/__init__.py
src/cs/ploneformdemo/configure.zcml
src/cs/ploneformdemo/interfaces.py
src/cs/ploneformdemo/permissions.zcml
src/cs/ploneformdemo/setuphandlers.py
src/cs/ploneformdemo/testing.py
src/cs/ploneformdemo/browser/__init__.py
src/cs/ploneformdemo/browser/configure.zcml
src/cs/ploneformdemo/browser/overrides/.gitkeep
src/cs/ploneformdemo/browser/static/.gitkeep
src/cs/ploneformdemo/locales/README.rst
src/cs/ploneformdemo/locales/__init__.py
src/cs/ploneformdemo/locales/cs.ploneformdemo.pot
src/cs/ploneformdemo/locales/update.py
src/cs/ploneformdemo/locales/update.sh
src/cs/ploneformdemo/locales/en/LC_MESSAGES/cs.ploneformdemo.mo
src/cs/ploneformdemo/locales/en/LC_MESSAGES/cs.ploneformdemo.po
src/cs/ploneformdemo/profiles/default/browserlayer.xml
src/cs/ploneformdemo/profiles/default/catalog.xml
src/cs/ploneformdemo/profiles/default/metadata.xml
src/cs/ploneformdemo/profiles/default/rolemap.xml
src/cs/ploneformdemo/profiles/default/registry/main.xml
src/cs/ploneformdemo/profiles/uninstall/browserlayer.xml
src/cs/ploneformdemo/tests/__init__.py
src/cs/ploneformdemo/tests/test_robot.py
src/cs/ploneformdemo/tests/test_setup.py
src/cs/ploneformdemo/tests/robot/test_example.robot
src/cs/ploneformdemo/views/__init__.py
src/cs/ploneformdemo/views/configure.zcml
src/cs/ploneformdemo/views/test_form_view.py