Metadata-Version: 2.1
Name: cs.ploneformdemo
Version: 1.0
Summary: An add-on for Plone to create a demo form with all available field types
Home-page: https://github.com/collective/cs.ploneformdemo
Author: Mikel Larreategi
Author-email: mlarreategi@codesyntax.com
License: GPL version 2
Project-URL: PyPI, https://pypi.python.org/pypi/cs.ploneformdemo
Project-URL: Source, https://github.com/collective/cs.ploneformdemo
Project-URL: Tracker, https://github.com/collective/cs.ploneformdemo/issues
Keywords: Python Plone CMS
Platform: UNKNOWN
Classifier: Environment :: Web Environment
Classifier: Framework :: Plone
Classifier: Framework :: Plone :: Addon
Classifier: Framework :: Plone :: 5.2
Classifier: Programming Language :: Python
Classifier: Programming Language :: Python :: 2.7
Classifier: Programming Language :: Python :: 3.7
Classifier: Operating System :: OS Independent
Classifier: License :: OSI Approved :: GNU General Public License v2 (GPLv2)
Requires-Python: ==2.7, >=3.6
Provides-Extra: test
